topsisx/__init__.py
topsisx/ahp.py
topsisx/api.py
topsisx/app.py
topsisx/cli.py
topsisx/dashboard.py
topsisx/entropy.py
topsisx/pipeline.py
topsisx/reports.py
topsisx/topsis.py
topsisx/utils.py
topsisx/verify_algorithms.py
topsisx/vikor.py
topsisx/visualizations.py
topsisx-0.2.3.dist-info/licenses/LICENSE
topsisx-0.2.3.dist-info/METADATA
topsisx-0.2.3.dist-info/WHEEL
topsisx-0.2.3.dist-info/entry_points.txt
topsisx-0.2.3.dist-info/top_level.txt
topsisx-0.2.3.dist-info/RECORD
