Metadata-Version: 2.4
Name: topsisx
Version: 0.2.3
Summary: A Python library for Multi-Criteria Decision Making (TOPSIS, AHP, VIKOR, Entropy) with Web Interface
Home-page: https://github.com/SuvitKumar003/ranklib
Author: Suvit Kumar
Author-email: suvitkumar03@gmail.com
Project-URL: Bug Reports, https://github.com/SuvitKumar003/ranklib/issues
Project-URL: Source, https://github.com/SuvitKumar003/ranklib
Project-URL: Documentation, https://github.com/SuvitKumar003/ranklib/blob/main/README.md
Keywords: mcdm,topsis,ahp,vikor,entropy,decision-making,multi-criteria,operations-research,optimization
Classifier: Development Status :: 4 - Beta
Classifier: Intended Audience :: Science/Research
Classifier: Intended Audience :: Developers
Classifier: Topic :: Scientific/Engineering
Classifier: Topic :: Scientific/Engineering :: Information Analysis
Classifier: Programming Language :: Python :: 3
Classifier: Programming Language :: Python :: 3.8
Classifier: Programming Language :: Python :: 3.9
Classifier: Programming Language :: Python :: 3.10
Classifier: Programming Language :: Python :: 3.11
Classifier: License :: OSI Approved :: MIT License
Classifier: Operating System :: OS Independent
Requires-Python: >=3.8
License-File: LICENSE
Requires-Dist: pandas>=2.0.0
Requires-Dist: numpy>=1.24.0
Requires-Dist: matplotlib>=3.8.0
Requires-Dist: streamlit>=1.34.0
Requires-Dist: fpdf>=1.7.2
Provides-Extra: api
Requires-Dist: fastapi>=0.110.0; extra == "api"
Requires-Dist: uvicorn>=0.23.0; extra == "api"
Provides-Extra: dev
Requires-Dist: pytest>=8.2.0; extra == "dev"
Requires-Dist: flake8>=7.0.0; extra == "dev"
Requires-Dist: black>=24.3.0; extra == "dev"
Dynamic: author
Dynamic: author-email
Dynamic: classifier
Dynamic: description
Dynamic: description-content-type
Dynamic: home-page
Dynamic: keywords
Dynamic: license-file
Dynamic: project-url
Dynamic: provides-extra
Dynamic: requires-dist
Dynamic: requires-python
Dynamic: summary
